akool_streaming_avatar/__init__.py
akool_streaming_avatar/client.py
akool_streaming_avatar/exceptions.py
akool_streaming_avatar/service_discovery.py
akool_streaming_avatar/websocket_client.py
akool_streaming_avatar-0.1.8.dist-info/licenses/LICENSE
akool_streaming_avatar-0.1.8.dist-info/METADATA
akool_streaming_avatar-0.1.8.dist-info/WHEEL
akool_streaming_avatar-0.1.8.dist-info/top_level.txt
akool_streaming_avatar-0.1.8.dist-info/RECORD
