Metadata-Version: 2.4
Name: akool-streaming-avatar
Version: 0.1.8
Summary: Python SDK for Akool Streaming Avatar WebSocket API
Author-email: Akool Team <support@akool.com>
License: MIT
Project-URL: Homepage, https://gitlab.akool.com/algorithm/akool_streaming_avatar_sdk
Project-URL: Documentation, https://gitlab.akool.com/algorithm/akool_streaming_avatar_sdk#readme
Project-URL: Repository, https://gitlab.akool.com/algorithm/akool_streaming_avatar_sdk.git
Project-URL: Issues, https://gitlab.akool.com/algorithm/akool_streaming_avatar_sdk/-/issues
Project-URL: Changelog, https://gitlab.akool.com/algorithm/akool_streaming_avatar_sdk/-/releases
Keywords: akool,streaming,avatar,websocket,audio,real-time
Classifier: Development Status :: 4 - Beta
Classifier: Intended Audience :: Developers
Classifier: Operating System :: OS Independent
Classifier: Programming Language :: Python :: 3
Classifier: Programming Language :: Python :: 3.8
Classifier: Programming Language :: Python :: 3.9
Classifier: Programming Language :: Python :: 3.10
Classifier: Programming Language :: Python :: 3.11
Classifier: Programming Language :: Python :: 3.12
Classifier: Topic :: Communications
Classifier: Topic :: Internet :: WWW/HTTP :: Dynamic Content
Classifier: Topic :: Multimedia :: Sound/Audio
Classifier: Topic :: Software Development :: Libraries :: Python Modules
Requires-Python: >=3.8
License-File: LICENSE
Requires-Dist: websockets>=14.0.0
Requires-Dist: aiohttp>=3.8.0
Requires-Dist: pydantic>=2.0.0
Requires-Dist: typing-extensions>=4.0.0
Provides-Extra: dev
Requires-Dist: pytest>=7.0.0; extra == "dev"
Requires-Dist: pytest-asyncio>=0.21.0; extra == "dev"
Requires-Dist: black>=23.0.0; extra == "dev"
Requires-Dist: flake8>=6.0.0; extra == "dev"
Requires-Dist: mypy>=1.0.0; extra == "dev"
Requires-Dist: pre-commit>=3.0.0; extra == "dev"
Provides-Extra: test
Requires-Dist: pytest>=7.0.0; extra == "test"
Requires-Dist: pytest-asyncio>=0.21.0; extra == "test"
Requires-Dist: pytest-cov>=4.0.0; extra == "test"
Requires-Dist: websockets>=11.0.0; extra == "test"
Dynamic: license-file
